mi_core_api_client_test_sdk/__init__.py
mi_core_api_client_test_sdk/api/__init__.py
mi_core_api_client_test_sdk/api/admin_api_keys/__init__.py
mi_core_api_client_test_sdk/api/admin_api_keys/delete_api_key_admin_api_keys_id_delete.py
mi_core_api_client_test_sdk/api/admin_api_keys/get_all_api_keys_admin_api_keys_get.py
mi_core_api_client_test_sdk/api/admin_api_keys/get_api_key_by_id_admin_api_keys_id_get.py
mi_core_api_client_test_sdk/api/admin_api_keys/update_api_key_admin_api_keys_id_patch.py
mi_core_api_client_test_sdk/api/admin_invite_codes/__init__.py
mi_core_api_client_test_sdk/api/admin_invite_codes/create_invite_code_admin_invite_codes_post.py
mi_core_api_client_test_sdk/api/admin_invite_codes/delete_invite_code_admin_invite_codes_code_delete.py
mi_core_api_client_test_sdk/api/admin_invite_codes/get_all_invite_codes_admin_invite_codes_get.py
mi_core_api_client_test_sdk/api/admin_storyboards/__init__.py
mi_core_api_client_test_sdk/api/admin_storyboards/get_all_storyboards_admin_storyboards_get.py
mi_core_api_client_test_sdk/api/admin_users/__init__.py
mi_core_api_client_test_sdk/api/admin_users/delete_user_admin_users_email_delete.py
mi_core_api_client_test_sdk/api/admin_users/get_all_users_admin_users_get.py
mi_core_api_client_test_sdk/api/admin_users/get_user_by_email_admin_users_email_get.py
mi_core_api_client_test_sdk/api/admin_users/update_user_admin_users_email_patch.py
mi_core_api_client_test_sdk/api/analyze/__init__.py
mi_core_api_client_test_sdk/api/analyze/delete_graph_entities_analyze_id_delete.py
mi_core_api_client_test_sdk/api/analyze/get_entities_analyze_post.py
mi_core_api_client_test_sdk/api/analyze/get_graph_entities_analyze_id_get.py
mi_core_api_client_test_sdk/api/analyze/get_graph_extraction_generation_status_analyze_id_status_get.py
mi_core_api_client_test_sdk/api/analyze/regenerate_graph_entities_analyze_id_patch.py
mi_core_api_client_test_sdk/api/api_keys/__init__.py
mi_core_api_client_test_sdk-0.1.0.dist-info/METADATA
mi_core_api_client_test_sdk-0.1.0.dist-info/WHEEL
mi_core_api_client_test_sdk-0.1.0.dist-info/RECORD
